byneuron/__init__.py
byneuron/byneuron.py
bn_byneuron-0.0.102.dist-info/METADATA
bn_byneuron-0.0.102.dist-info/WHEEL
bn_byneuron-0.0.102.dist-info/top_level.txt
bn_byneuron-0.0.102.dist-info/RECORD
