Metadata-Version: 2.1
Name: bn-byneuron
Version: 0.0.102
Summary: API for byneuron backend
Home-page: https://gitlab.com/bynubian/bynode/python_packages/byneuron
Author: jovi
Author-email: jo.vinckier@bynubian.com
License: UNKNOWN
Platform: UNKNOWN
Classifier: Programming Language :: Python :: 3
Classifier: License :: OSI Approved :: MIT License
Classifier: Operating System :: OS Independent
Requires-Python: >=3.7
Requires-Dist: requests>=2.32.4
